ercaspy/__about__.py
ercaspy/__init__.py
ercaspy/_api_call.py
ercaspy/_checkout.py
ercaspy/_config.py
ercaspy/error.py
ercaspy-0.0.1.dist-info/METADATA
ercaspy-0.0.1.dist-info/WHEEL
ercaspy-0.0.1.dist-info/licenses/LICENSE
ercaspy-0.0.1.dist-info/RECORD
