Metadata-Version: 2.3
Name: ercaspy
Version: 0.0.1
Summary: Python Library for Ercas Pay API
Project-URL: Documentation, https://github.com/Ifechukwu T. Ogidi/ercaspy#readme
Project-URL: Issues, https://github.com/Ifechukwu T. Ogidi/ercaspy/issues
Project-URL: Source, https://github.com/Ifechukwu T. Ogidi/ercaspy
Author-email: "Ifechukwu T. Ogidi" <ogidiifechukwu6@gmail.com>
License: MIT
Classifier: Development Status :: 4 - Beta
Classifier: Programming Language :: Python
Classifier: Programming Language :: Python :: 3.8
Classifier: Programming Language :: Python :: 3.9
Classifier: Programming Language :: Python :: 3.10
Classifier: Programming Language :: Python :: 3.11
Classifier: Programming Language :: Python :: 3.12
Classifier: Programming Language :: Python :: Implementation :: CPython
Classifier: Programming Language :: Python :: Implementation :: PyPy
Requires-Python: >=3.8
